makepyz/__init__.py
makepyz/__main__.py
makepyz/api.py
makepyz/cli.py
makepyz/exceptions.py
makepyz/fileops.py
makepyz/github.py
makepyz/misc.py
makepyz/packaging.py
makepyz/py.typed
makepyz/scm.py
makepyz/tasks.py
makepyz/tasks_gh.py
makepyz/text.py
makepyz/tree.py
makepyz/scripts/makepyzui.py
makepyz-0.0.1.dist-info/METADATA
makepyz-0.0.1.dist-info/WHEEL
makepyz-0.0.1.dist-info/entry_points.txt
makepyz-0.0.1.dist-info/top_level.txt
makepyz-0.0.1.dist-info/RECORD
